UMP_flask/__init__.py
UMP_flask/configuration.py
UMP_flask/models.py
UMP_flask/views.py
UMP_flask/templates/security/default.html
UMP_flask-0.0.1.dist-info/LICENSE
UMP_flask-0.0.1.dist-info/METADATA
UMP_flask-0.0.1.dist-info/WHEEL
UMP_flask-0.0.1.dist-info/top_level.txt
UMP_flask-0.0.1.dist-info/RECORD
