Metadata-Version: 2.1
Name: UMP_flask
Version: 0.0.1
Summary: User Management Package
Author: Mostafa Abdelsatar
Author-email: mostafa.jamal.mjm@gmail.com
Project-URL: source, https://github.com/Mostafa1Jamal1/UMP-flask/
Classifier: Development Status :: 3 - Alpha
Classifier: Programming Language :: Python :: 3
Classifier: License :: OSI Approved :: MIT License
Classifier: Operating System :: OS Independent
License-File: LICENSE
Requires-Dist: flask
Requires-Dist: flask-security
Requires-Dist: flask-mail
Requires-Dist: mongoengine
Requires-Dist: python-dotenv
